LSD/__init__.py
LSD/__main__.py
LSD/RMQ/__init__.py
LSD/all_in_one/__init__.py
LSD/all_in_one/__init__2.py
LSD/auxiliary_graph/__init__.py
LSD/colorgraph/__init__.py
LSD/colors/__init__.py
LSD/cycle_decomp/__init__.py
LSD/cycles/__init__.py
LSD/cycles/cover.py
LSD/dag_creation/__init__.py
LSD/dag_creation/roots.py
LSD/dag_creation/sung.py
LSD/detecter/__init__.py
LSD/detecter/brankovic.py
LSD/detecter/gaertner.py
LSD/detecter/onodera.py
LSD/detecter/outvalues.py
LSD/detecter/topologicsorting.py
LSD/dfs_tree/__init__.py
LSD/dfs_tree/order.py
LSD/filter/__init__.py
LSD/hashed_list/__init__.py
LSD/inout/__init__.py
LSD/order/__init__.py
LSD/partition/__init__.py
LSD/paths/__init__.py
LSD/paths/dp.py
LSD/paths/max_c_path.py
LSD/reporter/__init__.py
LSD/roots/__init__.py
LSD/tools/__init__.py
LSD/tools/__main__.py
LSD/tools/onoworst.py
LSD/tools/sourcereach.py
LSD/topological_sorting/__init__.py
LSD_Bubble-2.0.dist-info/METADATA
LSD_Bubble-2.0.dist-info/RECORD
LSD_Bubble-2.0.dist-info/WHEEL
LSD_Bubble-2.0.dist-info/entry_points.txt
LSD_Bubble-2.0.dist-info/top_level.txt
