Metadata-Version: 2.1
Name: LSD-Bubble
Version: 2.0
Summary: Detect all superbubbles in a graph.
Home-page: https://github.com/Fabianexe/Superbubble
Author: Fabian Gaertner
Author-email: fabian@bioinf.uni-leipzig.de
License: BSD 3-Clause
Keywords: graph,superbubble,﻿de Bruijn graph,﻿Genome assembly,﻿Linear time algorithm
Platform: UNKNOWN
Classifier: Development Status :: 5 - Production/Stable
Classifier: Environment :: Console
Classifier: License :: OSI Approved :: BSD License
Classifier: Natural Language :: English
Classifier: Operating System :: OS Independent
Classifier: Programming Language :: Python :: 3
Classifier: Programming Language :: Python :: 3.6
Classifier: Programming Language :: Python :: 3.7
Classifier: Intended Audience :: Developers
Classifier: Intended Audience :: Science/Research
Classifier: Topic :: Scientific/Engineering :: Bio-Informatics
Requires-Dist: networkx (>=2.1)
